pyRegions
